Metadata-Version: 1.0
Name: dnsd031-binomialPypi
Version: 0.1
Summary: Gaussian and Binomial distribution
Home-page: UNKNOWN
Author: Rakoto031
Author-email: UNKNOWN
License: UNKNOWN
Platform: UNKNOWN
